my_rust_lib-0.1.0.dist-info/METADATA
my_rust_lib-0.1.0.dist-info/WHEEL
my_rust_lib/__init__.py
my_rust_lib/my_rust_lib.cpython-310-x86_64-linux-gnu.so
my_rust_lib-0.1.0.dist-info/RECORD
