Metadata-Version: 2.3
Name: my_rust_lib
Version: 0.1.0
Summary: A Rust library that provides an add function for both Rust and Python.
Author: Kabelo Masemola<kabelo.masemola@maskab.co.za
Author-email: Kabelo Masemola<kabelo.masemola@maskab.co.za
License: MIT
